sporco/__init__.py
sporco/_util.py
sporco/array.py
sporco/cdict.py
sporco/cnvrep.py
sporco/common.py
sporco/fft.py
sporco/interp.py
sporco/linalg.py
sporco/metric.py
sporco/mpiutil.py
sporco/plot.py
sporco/signal.py
sporco/util.py
sporco/admm/__init__.py
sporco/admm/admm.py
sporco/admm/bpdn.py
sporco/admm/cbpdn.py
sporco/admm/cbpdnin.py
sporco/admm/cbpdntv.py
sporco/admm/ccmod.py
sporco/admm/ccmodmd.py
sporco/admm/cmod.py
sporco/admm/parcbpdn.py
sporco/admm/pdcsc.py
sporco/admm/ppp.py
sporco/admm/rpca.py
sporco/admm/spline.py
sporco/admm/tvl1.py
sporco/admm/tvl2.py
sporco/cuda/__init__.py
sporco/cupy/__init__.py
sporco/cupy/_cp_util.py
sporco/cupy/_gputil.py
sporco/cupy/_nogputil.py
sporco/cupy/_np_util.py
sporco/cupy/admm/__init__.py
sporco/cupy/dictlrn/__init__.py
sporco/cupy/pgm/__init__.py
sporco/data/README.rst
sporco/data/barbara.png
sporco/data/convdict.npz
sporco/data/kodim23.png
sporco/data/monarch.png
sporco/data/sail.png
sporco/data/tulips.png
sporco/dictlrn/__init__.py
sporco/dictlrn/bpdndl.py
sporco/dictlrn/cbpdndl.py
sporco/dictlrn/cbpdndlmd.py
sporco/dictlrn/common.py
sporco/dictlrn/dictlrn.py
sporco/dictlrn/onlinecdl.py
sporco/dictlrn/prlcnscdl.py
sporco/dictlrn/wbpdndl.py
sporco/pgm/__init__.py
sporco/pgm/backtrack.py
sporco/pgm/bpdn.py
sporco/pgm/cbpdn.py
sporco/pgm/ccmod.py
sporco/pgm/cmod.py
sporco/pgm/momentum.py
sporco/pgm/pgm.py
sporco/pgm/ppp.py
sporco/pgm/stepsize.py
sporco/prox/__init__.py
sporco/prox/_dl1l2.py
sporco/prox/_l1proj.py
sporco/prox/_l21.py
sporco/prox/_lp.py
sporco/prox/_nuclear.py
sporco/prox/_util.py
sporco-0.2.2.post1.data/data/share/doc/sporco-0.2.2.post1/examples/scripts/index.rst
sporco-0.2.2.post1.data/data/share/doc/sporco-0.2.2.post1/examples/scripts/cdl/cbpdndl_cns_gry.py
sporco-0.2.2.post1.data/data/share/doc/sporco-0.2.2.post1/examples/scripts/cdl/cbpdndl_grd.py
sporco-0.2.2.post1.data/data/share/doc/sporco-0.2.2.post1/examples/scripts/cdl/cbpdndl_jnt_clr.py
sporco-0.2.2.post1.dist-info/licenses/LICENSE
sporco-0.2.2.post1.dist-info/METADATA
sporco-0.2.2.post1.dist-info/WHEEL
sporco-0.2.2.post1.dist-info/top_level.txt
sporco-0.2.2.post1.dist-info/RECORD
