Metadata-Version: 2.4
Name: sporco
Version: 0.2.2.post1
Summary: Sparse Optimisation Research Code: A Python package for sparse coding and dictionary learning
Home-page: https://github.com/bwohlberg/sporco
Author: Brendt Wohlberg
Author-email: brendt@ieee.org
License: BSD-3-Clause
Keywords: Sparse Representations,Sparse Coding,Dictionary Learning,Convolutional Sparse Representations,Convolutional Sparse Coding,Optimization,ADMM,PGM
Platform: Any
Classifier: Development Status :: 4 - Beta
Classifier: Intended Audience :: Education
Classifier: Intended Audience :: Science/Research
Classifier: Operating System :: OS Independent
Classifier: Programming Language :: Python :: 2.7
Classifier: Programming Language :: Python :: 3
Classifier: Topic :: Scientific/Engineering :: Information Analysis
Classifier: Topic :: Scientific/Engineering :: Mathematics
Classifier: Topic :: Software Development :: Libraries :: Python Modules
License-File: LICENSE
Requires-Dist: future
Requires-Dist: numpy
Requires-Dist: scipy
Requires-Dist: imageio
Requires-Dist: filetype
Requires-Dist: matplotlib
Requires-Dist: pyfftw
Provides-Extra: tests
Requires-Dist: pytest; extra == "tests"
Requires-Dist: pytest-runner; extra == "tests"
Provides-Extra: docs
Requires-Dist: sphinx>=2.2; extra == "docs"
Requires-Dist: numpydoc; extra == "docs"
Requires-Dist: sphinxcontrib-bibtex; extra == "docs"
Requires-Dist: sphinx_tabs; extra == "docs"
Requires-Dist: sphinx_fontawesome; extra == "docs"
Requires-Dist: jonga; extra == "docs"
Requires-Dist: ipython>=6.3.1; extra == "docs"
Requires-Dist: jupyter; extra == "docs"
Requires-Dist: py2jn; extra == "docs"
Requires-Dist: pypandoc; extra == "docs"
Provides-Extra: gpu
Requires-Dist: cupy; extra == "gpu"
Requires-Dist: gputil; extra == "gpu"
Requires-Dist: wurlitzer; extra == "gpu"
Provides-Extra: optional
Requires-Dist: numexpr; extra == "optional"
Requires-Dist: mpldatacursor; extra == "optional"
Dynamic: author
Dynamic: author-email
Dynamic: classifier
Dynamic: description
Dynamic: home-page
Dynamic: keywords
Dynamic: license
Dynamic: license-file
Dynamic: platform
Dynamic: provides-extra
Dynamic: requires-dist
Dynamic: summary
